rest_wdclient/Wanda_MLserving.py
rest_wdclient/__init__.py
wdmlservice-0.1.1.dist-info/DESCRIPTION.rst
wdmlservice-0.1.1.dist-info/METADATA
wdmlservice-0.1.1.dist-info/RECORD
wdmlservice-0.1.1.dist-info/WHEEL
wdmlservice-0.1.1.dist-info/metadata.json
wdmlservice-0.1.1.dist-info/top_level.txt
