Metadata-Version: 2.0
Name: wdmlservice
Version: 0.1.1
Summary: REST APIs for wanda machine learning service, made easy.
Home-page: https://github.com/leepand
Author: Li Pandeng
Author-email: pandeng.li@163.com
License: BSD
Platform: UNKNOWN
Requires-Dist: requests
